LICENSE
README.md
setup.cfg
setup.py
django_common_utils/__init__.py
django_common_utils/apps.py
django_common_utils/signals.py
django_common_utils/tests.py
django_common_utils.egg-info/PKG-INFO
django_common_utils.egg-info/SOURCES.txt
django_common_utils.egg-info/dependency_links.txt
django_common_utils.egg-info/requires.txt
django_common_utils.egg-info/top_level.txt
django_common_utils/constants/RFC.py
django_common_utils/constants/__init__.py
django_common_utils/constants/django.py
django_common_utils/libraries/__init__.py
django_common_utils/libraries/typings.py
django_common_utils/libraries/calendar/__init__.py
django_common_utils/libraries/calendar/actions.py
django_common_utils/libraries/calendar/constants.py
django_common_utils/libraries/fieldsets/__init__.py
django_common_utils/libraries/fieldsets/admin.py
django_common_utils/libraries/fieldsets/admin_mixins.py
django_common_utils/libraries/fieldsets/sections.py
django_common_utils/libraries/fieldsets/mixins/__init__.py
django_common_utils/libraries/fieldsets/mixins/base.py
django_common_utils/libraries/fieldsets/mixins/date.py
django_common_utils/libraries/fieldsets/mixins/text.py
django_common_utils/libraries/fieldsets/mixins/url.py
django_common_utils/libraries/fieldsets/mixins/user.py
django_common_utils/libraries/forms/__init__.py
django_common_utils/libraries/forms/mixins/__init__.py
django_common_utils/libraries/forms/mixins/common.py
django_common_utils/libraries/handlers/__init__.py
django_common_utils/libraries/handlers/constants.py
django_common_utils/libraries/handlers/handlers.py
django_common_utils/libraries/handlers/models.py
django_common_utils/libraries/handlers/typings.py
django_common_utils/libraries/handlers/mixins/__init__.py
django_common_utils/libraries/handlers/mixins/base.py
django_common_utils/libraries/handlers/mixins/html.py
django_common_utils/libraries/handlers/mixins/text.py
django_common_utils/libraries/handlers/optimizers/__init__.py
django_common_utils/libraries/handlers/optimizers/html.py
django_common_utils/libraries/handlers/optimizers/text.py
django_common_utils/libraries/models/__init__.py
django_common_utils/libraries/models/get_settings.py
